stactools/cop_dem/__init__.py
stactools/cop_dem/commands.py
stactools/cop_dem/constants.py
stactools/cop_dem/stac.py
stactools_cop_dem-0.4.1.dist-info/LICENSE
stactools_cop_dem-0.4.1.dist-info/METADATA
stactools_cop_dem-0.4.1.dist-info/WHEEL
stactools_cop_dem-0.4.1.dist-info/top_level.txt
stactools_cop_dem-0.4.1.dist-info/RECORD
