Metadata-Version: 2.1
Name: stactools-cop-dem
Version: 0.4.1
Summary: stactools package for Copernicus Digital Elevation Model
Home-page: https://github.com/stactools-packages/cop-dem
Author: Justin Fisk
Author-email: misterfisk@gmail.com
Project-URL: Documentation, https://stactools-cop-dem.readthedocs.io/en/latest/
Project-URL: Issues, https://github.com/stactools-packages/cop-dem/issues
Keywords: stactools,pystac,catalog,STAC,Copernicus,dem,elevation,raster
Classifier: Development Status :: 4 - Beta
Classifier: License :: OSI Approved :: Apache Software License
Classifier: Programming Language :: Python :: 3.8
Classifier: Programming Language :: Python :: 3.9
Classifier: Programming Language :: Python :: 3.10
Classifier: Programming Language :: Python :: 3.11
License-File: LICENSE
Requires-Dist: stactools[s3] (>=0.4.1)
